spot/__init__.py
spot/version.py
spot/config/hsc_info.json
spot/config/pfs_info.json
spot/config/sites.yml
spot/config/skycams.yml
spot/doc/__init__.py
spot/examples/TelescopePosition_Companion.py
spot/icons/__init__.py
spot/icons/blue_arr_dn.svg
spot/icons/blue_arr_up.svg
spot/icons/green_arr_dn.svg
spot/icons/green_arr_up.svg
spot/icons/no_go.svg
spot/icons/orange_arr_dn.svg
spot/icons/orange_arr_up.svg
spot/icons/purple_arr_dn.svg
spot/icons/purple_arr_up.svg
spot/icons/red_arr_dn.svg
spot/icons/red_arr_up.svg
spot/icons/spot.svg
spot/icons/yellow_arr_dn.svg
spot/icons/yellow_arr_up.svg
spot/instruments/__init__.py
spot/instruments/subaru.py
spot/plots/__init__.py
spot/plots/altitude.py
spot/plugins/CPanel.py
spot/plugins/FindImage.py
spot/plugins/InsFov.py
spot/plugins/LGS.py
spot/plugins/PolarSky.py
spot/plugins/SPOTMenubar.py
spot/plugins/SPOTToolbar.py
spot/plugins/SiteSelector.py
spot/plugins/SkyCam.py
spot/plugins/TargetGenerator.py
spot/plugins/Targets.py
spot/plugins/TelescopePosition.py
spot/plugins/Visibility.py
spot/plugins/__init__.py
spot/util/__init__.py
spot/util/calcpos.py
spot/util/eph_cache.py
spot/util/pamsat.py
spot/util/polar.py
spot/util/rot.py
spot/util/sites.py
spot/util/target.py
spot_nik-1.0.1.data/scripts/pam_w.py
spot_nik-1.0.1.data/scripts/spot
spot_nik-1.0.1.data/scripts/spot.bat
spot_nik-1.0.1.dist-info/licenses/LICENSE.md
spot_nik-1.0.1.dist-info/METADATA
spot_nik-1.0.1.dist-info/WHEEL
spot_nik-1.0.1.dist-info/top_level.txt
spot_nik-1.0.1.dist-info/RECORD
