Metadata-Version: 2.4
Name: spot-nik
Version: 1.0.1
Summary: Site Planning and Observation Tool
Home-page: https://github.com/naojsoft/spot
Author: SPOT Maintainers
Author-email: ocs@naoj.org
License: BSD
Keywords: site,telescope,astronomy,observation,planning,plugins
Classifier: Intended Audience :: Science/Research
Classifier: License :: OSI Approved :: BSD License
Classifier: Operating System :: OS Independent
Classifier: Programming Language :: Python :: 3
Classifier: Topic :: Scientific/Engineering :: Astronomy
Classifier: Topic :: Scientific/Engineering :: Physics
Requires-Python: >=3.11
License-File: LICENSE.md
Requires-Dist: astropy>=6.0.1
Requires-Dist: jplephem>=2.21
Requires-Dist: skyfield>=1.48
Requires-Dist: astroquery>=0.4.7
Requires-Dist: python-dateutil>=2.8.2
Requires-Dist: matplotlib>=3.8
Requires-Dist: pandas>=0.24.1
Requires-Dist: ginga>=5.4.0
Requires-Dist: requests>=2.26.0
Provides-Extra: docs
Requires-Dist: sphinx; extra == "docs"
Requires-Dist: sphinx_rtd_theme; extra == "docs"
Dynamic: license-file
